undatasio/__init__.py
undatasio/undatasio.py
undatasio-0.2.0.2.dist-info/LICENSE
undatasio-0.2.0.2.dist-info/METADATA
undatasio-0.2.0.2.dist-info/WHEEL
undatasio-0.2.0.2.dist-info/top_level.txt
undatasio-0.2.0.2.dist-info/RECORD
