Metadata-Version: 2.1
Name: undatasio
Version: 0.2.0.2
Summary: python sdk for the undatasio platform
Home-page: 
Author: undatasio
Author-email: alex.zhang@undatas.io
License: MIT
Requires-Python: >=3.10
License-File: LICENSE
Requires-Dist: requests~=2.32.3
